Metadata-Version: 2.1
Name: fastapi-modelrouter
Version: 0.1.1
Summary: FastAPI Router that creates CRUD routes for SqlAlchemy models
Home-page: https://github.com/UweWindt/fastapi-modelrouter
Author: Uwe Windt
Author-email: uwe.windt@windisoft.de
License: MIT
Keywords: fastapi router sqlalchemy development
Classifier: Development Status :: 3 - Alpha
Classifier: Intended Audience :: Developers
Classifier: Topic :: Software Development :: Build Tools
Classifier: License :: OSI Approved :: MIT License
Classifier: Programming Language :: Python :: 3.7
Classifier: Programming Language :: Python :: 3.8
Classifier: Programming Language :: Python :: 3.9
Classifier: Programming Language :: Python :: 3.10
Classifier: Programming Language :: Python :: 3.11
License-File: LICENSE
